db/__init__.py
db/db.py
dbmini-0.2.0.dist-info/METADATA
dbmini-0.2.0.dist-info/WHEEL
dbmini-0.2.0.dist-info/top_level.txt
dbmini-0.2.0.dist-info/RECORD
