Metadata-Version: 2.4
Name: dbmini
Version: 0.2.0
Summary: A simple DB connector for MySQL, SQLite, and MongoDB
Home-page: https://github.com/prathamesh9669/dbmini
Author: Prathamesh Patil 
Author-email: Prathamesh Patil <prathameshpatil0545@gmail.com>
Requires-Python: >=3.7
Requires-Dist: mysql-connector-python
Requires-Dist: pymongo
Dynamic: author
Dynamic: home-page
Dynamic: requires-python
